setup.cfg
setup.py
MiniMockUnit.egg-info/PKG-INFO
MiniMockUnit.egg-info/SOURCES.txt
MiniMockUnit.egg-info/dependency_links.txt
MiniMockUnit.egg-info/entry_points.txt
MiniMockUnit.egg-info/not-zip-safe
MiniMockUnit.egg-info/requires.txt
MiniMockUnit.egg-info/top_level.txt
mm_unit/__init__.py