Metadata-Version: 1.0
Name: MiniMockUnit
Version: 0.1-r0
Summary: Utilities for unit testing with MiniMock
Home-page: http://www.webmynd.com
Author: James Brady, WebMynd Corp.
Author-email: founders@webmynd.com
License: BSD
Platform: UNKNOWN
Classifier: Development Status :: 3 - Alpha
Classifier: Intended Audience :: Developers
Classifier: License :: OSI Approved :: BSD License
Classifier: Topic :: Software Development :: Testing
